pyaibridge/__init__.py
pyaibridge-0.0.1.dist-info/METADATA
pyaibridge-0.0.1.dist-info/WHEEL
pyaibridge-0.0.1.dist-info/RECORD
