Metadata-Version: 2.4
Name: pyaibridge
Version: 0.0.1
Summary: High-performance unified API for all LLM providers
Project-URL: Homepage, https://github.com/yourusername/aibridge
Project-URL: Repository, https://github.com/yourusername/aibridge
Author-email: Your Name <your.email@example.com>
License: MIT
Classifier: Development Status :: 1 - Planning
Classifier: Intended Audience :: Developers
Classifier: License :: OSI Approved :: MIT License
Classifier: Programming Language :: Python :: 3
Classifier: Programming Language :: Python :: 3.9
Classifier: Programming Language :: Python :: 3.10
Classifier: Programming Language :: Python :: 3.11
Classifier: Programming Language :: Python :: 3.12
Requires-Python: >=3.9
